LICENSE
MANIFEST.in
README.rst
setup.py
doc/conf.py
doc/examples.rst
doc/features.rst
doc/index.rst
doc/install.rst
doc/introduction.rst
doc/optics.rst
doc/physics.rst
doc/tutorial.rst
examples/ac/unipolar-prl100.ipynb
examples/diffusion/diffusion.ipynb
examples/egdm/egdm-g1-g2-g3.ipynb
examples/egdm/image-force-prb79.ipynb
examples/egdm/unipolar-prb78.ipynb
examples/interactive/pn.ipynb
examples/ionic/diluted-electrolyte.ipynb
examples/ionic/electrochemical-doping-japplphys113.ipynb
examples/light-emitting/doping-dynamics-orgel12.ipynb
examples/light-emitting/interfacial-feedback-prb66.ipynb
examples/numeric/fprecision.ipynb
examples/numeric/mesh-convergence.ipynb
examples/optical/multilayer-optics.ipynb
examples/optical/solar-spectra.ipynb
examples/photovoltaic/Voc-Ff.ipynb
examples/photovoltaic/transientphotocurrent-traps.ipynb
examples/scl/scl-trapping.ipynb
examples/scl/transient-with-trapping.ipynb
oedes/__init__.py
oedes/_version.py
oedes/ad.py
oedes/context.py
oedes/logs.py
oedes/model.py
oedes/param.py
oedes/sensitivity.py
oedes/solver.py
oedes/testing.py
oedes.egg-info/PKG-INFO
oedes.egg-info/SOURCES.txt
oedes.egg-info/dependency_links.txt
oedes.egg-info/requires.txt
oedes.egg-info/top_level.txt
oedes/functions/__init__.py
oedes/functions/brent.py
oedes/functions/egdm.py
oedes/functions/gdos.py
oedes/functions/optical.py
oedes/functions/physics.py
oedes/functions/rc.py
oedes/functions/scharfgum.py
oedes/functions/tests/__init__.py
oedes/functions/tests/test_functions.py
oedes/fvm/__init__.py
oedes/fvm/builder.py
oedes/fvm/cell.py
oedes/fvm/discrete.py
oedes/fvm/evaluator.py
oedes/fvm/mesh.py
oedes/fvm/poisson.py
oedes/fvm/transport.py
oedes/models/__init__.py
oedes/models/compose.py
oedes/models/deprecated.py
oedes/models/domain.py
oedes/models/egdm.py
oedes/models/solver.py
oedes/models/std.py
oedes/models/equations/__init__.py
oedes/models/equations/band.py
oedes/models/equations/base.py
oedes/models/equations/boltzmann.py
oedes/models/equations/boundary.py
oedes/models/equations/charged.py
oedes/models/equations/conserved.py
oedes/models/equations/deprecated.py
oedes/models/equations/dos.py
